bth_1208LS.py
mccBluetooth.py
test-bth1208LS.py
bluetooth_linux_drivers-0.1.dist-info/METADATA
bluetooth_linux_drivers-0.1.dist-info/WHEEL
bluetooth_linux_drivers-0.1.dist-info/top_level.txt
bluetooth_linux_drivers-0.1.dist-info/RECORD
